pyguara/__init__.py
pyguara/app_scene.py
pyguara/ai/__init__.py
pyguara/ai/ai_system.py
pyguara/ai/behavior_tree.py
pyguara/ai/blackboard.py
pyguara/ai/components.py
pyguara/ai/fsm.py
pyguara/ai/navmesh.py
pyguara/ai/pathfinding.py
pyguara/ai/steering.py
pyguara/ai/steering_system.py
pyguara/ai/pathfinding/astar.py
pyguara/ai/pathfinding/core.py
pyguara/ai/pathfinding/grid.py
pyguara/animation/__init__.py
pyguara/animation/easing.py
pyguara/animation/tween.py
pyguara/application/__init__.py
pyguara/application/application.py
pyguara/application/bootstrap.py
pyguara/application/sandbox.py
pyguara/audio/__init__.py
pyguara/audio/audio_source_system.py
pyguara/audio/audio_system.py
pyguara/audio/components.py
pyguara/audio/manager.py
pyguara/audio/types.py
pyguara/audio/backends/pygame/loaders.py
pyguara/audio/backends/pygame/pygame_audio.py
pyguara/audio/backends/pygame/types.py
pyguara/cli/__init__.py
pyguara/cli/atlas_generator.py
pyguara/cli/build.py
pyguara/common/components.py
pyguara/common/constants.py
pyguara/common/palette.py
pyguara/common/types.py
pyguara/config/__init__.py
pyguara/config/events.py
pyguara/config/manager.py
pyguara/config/types.py
pyguara/config/validation.py
pyguara/dev/__init__.py
pyguara/dev/file_watcher.py
pyguara/dev/hot_reload.py
pyguara/di/__init__.py
pyguara/di/container.py
pyguara/di/decorators.py
pyguara/di/exceptions.py
pyguara/di/types.py
pyguara/ecs/__init__.py
pyguara/ecs/archetype.py
pyguara/ecs/component.py
pyguara/ecs/entity.py
pyguara/ecs/manager.py
pyguara/ecs/query_cache.py
pyguara/editor/__init__.py
pyguara/editor/drawers.py
pyguara/editor/layer.py
pyguara/editor/panels/assets.py
pyguara/editor/panels/hierarchy.py
pyguara/editor/panels/inspector.py
pyguara/error/__init__.py
pyguara/error/exceptions.py
pyguara/error/handlers.py
pyguara/error/types.py
pyguara/events/__init__.py
pyguara/events/dispatcher.py
pyguara/events/input.py
pyguara/events/lifecycle.py
pyguara/events/protocols.py
pyguara/events/types.py
pyguara-0.4.0.dist-info/METADATA
pyguara-0.4.0.dist-info/WHEEL
pyguara-0.4.0.dist-info/entry_points.txt
pyguara-0.4.0.dist-info/licenses/LICENSE
pyguara-0.4.0.dist-info/RECORD
