Metadata-Version: 2.4
Name: pyguara
Version: 0.4.0
Summary: Python game engine featuring a event and data driven archictecture.
Author-email: Wedeueis Braz <wedeueisbraz@gmail.com>
License-File: LICENSE
Keywords: 2d,action-rpg,data-driven,event-driven,game-engine
Classifier: Development Status :: 3 - Alpha
Classifier: Intended Audience :: Developers
Classifier: License :: OSI Approved :: MIT License
Classifier: Programming Language :: Python :: 3
Classifier: Programming Language :: Python :: 3.12
Classifier: Topic :: Games/Entertainment
Classifier: Topic :: Software Development :: Libraries :: Python Modules
Requires-Python: >=3.12
Requires-Dist: click>=8.1.7
Requires-Dist: dataclasses-json>=0.6.0
Requires-Dist: moderngl>=5.8.0
Requires-Dist: msgpack>=1.1.2
Requires-Dist: numpy>=1.26.0
Requires-Dist: pillow>=12.1.0
Requires-Dist: pygame-ce>=2.5.6
Requires-Dist: pymunk>=7.2.0
Provides-Extra: benchmark
Requires-Dist: memory-profiler>=0.61.0; extra == 'benchmark'
Requires-Dist: py-spy>=0.3.0; extra == 'benchmark'
Requires-Dist: pytest-benchmark>=4.0.0; extra == 'benchmark'
Provides-Extra: build
Requires-Dist: pyinstaller>=6.0.0; extra == 'build'
Provides-Extra: dev
Requires-Dist: build>=0.10.0; extra == 'dev'
Requires-Dist: imgui>=2.0.0; extra == 'dev'
Requires-Dist: mypy>=1.0.0; extra == 'dev'
Requires-Dist: pillow>=11.3.0; extra == 'dev'
Requires-Dist: pre-commit>=3.0.0; extra == 'dev'
Requires-Dist: pytest-benchmark>=4.0.0; extra == 'dev'
Requires-Dist: pytest-cov>=4.0.0; extra == 'dev'
Requires-Dist: pytest-mock>=3.10.0; extra == 'dev'
Requires-Dist: pytest>=7.0.0; extra == 'dev'
Requires-Dist: ruff>=0.14.0; extra == 'dev'
Requires-Dist: syrupy>=4.9.1; extra == 'dev'
Requires-Dist: tox>=4.0.0; extra == 'dev'
Requires-Dist: twine>=4.0.0; extra == 'dev'
Provides-Extra: docs
Requires-Dist: mkdocs-material>=9.0.0; extra == 'docs'
Requires-Dist: mkdocs-mermaid2-plugin>=0.6.0; extra == 'docs'
Requires-Dist: mkdocs>=1.5.0; extra == 'docs'
Requires-Dist: pymdown-extensions>=10.0.0; extra == 'docs'
